{
    "Body": "File_unknown-png.png",
    "BodyLength": 2473,
    "ContentType": "image",
    "Description": "",
    "DeveloperName": "CACBBABEA26dbc8557e3849e2baeeb6b19413c29a",
    "IsBodySearchable": false,
    "IsInternalUseOnly": false,
    "IsPublic": true,
    "Keywords": "",
    "Name": "unknown.png",
    "Type": "png",
    "Url": "",
    "VlocityDataPackType": "SObject",
    "VlocityRecordSObjectType": "Document",
    "VlocityRecordSourceKey": "Document/CACBBABEA26dbc8557e3849e2baeeb6b19413c29a"
}